{
  "name": "TCBScans",
  "baseUrl": "https://tcbscans.me",
  "selectors": {
    "pages": {
      "container": "img",
      "imageAttribute": "src"
    },
    "search": {
      "url": "a",
      "title": "a.mb-3",
      "poster": "img",
      "container": ".bg-card",
      "searchUrl": "/projects"
    },
    "details": {
      "title": "h1",
      "genres": "",
      "poster": ".flex.items-center.justify-center > img",
      "status": "",
      "authors": "",
      "seriesType": "",
      "description": ".px-4.py-6 > p"
    },
    "chapters": {
      "url": "",
      "date": "",
      "title": "",
      "number": "",
      "container": ".col-span-2 > a"
    }
  },
  "parsing": {
    "dateFormat": "noOp",
    "chapterRegex": "Chapter (\\d+(\\.\\d+)?)",
    "statusMapping": {
      "_default": "ONGOING"
    }
  },
  "imageConfig": {}
}